sphinx_mdinclude/__init__.py
sphinx_mdinclude/__version__.py
sphinx_mdinclude/parse.py
sphinx_mdinclude/render.py
sphinx_mdinclude/sphinx.py
sphinx_mdinclude/tests/__init__.py
sphinx_mdinclude/tests/__main__.py
sphinx_mdinclude/tests/test.md
sphinx_mdinclude/tests/test.rst
sphinx_mdinclude/tests/test_renderer.py
sphinx_mdinclude/tests/test_smoke.py
sphinx_mdinclude-0.6.0.dist-info/LICENSE
sphinx_mdinclude-0.6.0.dist-info/WHEEL
sphinx_mdinclude-0.6.0.dist-info/METADATA
sphinx_mdinclude-0.6.0.dist-info/RECORD
