Metadata-Version: 2.1
Name: sphinx_mdinclude
Version: 0.6.0
Summary: Markdown extension for Sphinx
Keywords: Markdown,reStructuredText,sphinx-extension
Author-email: Hiroyuki Takagi <miyako.dev@gmail.com>, CrossNox <ijmermet+m2r2@gmail.com>, Amethyst Reese <amy@noswap.com>
Maintainer-email: Amethyst Reese <amy@noswap.com>
Requires-Python: >=3.8
Classifier: Development Status :: 4 - Beta
Classifier: Framework :: Sphinx :: Extension
Classifier: Intended Audience :: Developers
Classifier: License :: OSI Approved :: MIT License
Classifier: Natural Language :: English
Classifier: Topic :: Text Processing
Requires-Dist: mistune >=3.0,<4.0
Requires-Dist: docutils >=0.16,<1.0
Requires-Dist: pygments >= 2.8
Requires-Dist: docutils==0.20.1 ; extra == "dev" and ( python_version < '3.9')
Requires-Dist: docutils==0.21.1 ; extra == "dev" and ( python_version >= '3.9')
Requires-Dist: mistune==3.0.2 ; extra == "dev"
Requires-Dist: attribution==1.7.1 ; extra == "dev"
Requires-Dist: black==24.4.0 ; extra == "dev"
Requires-Dist: coverage==7.4.4 ; extra == "dev"
Requires-Dist: flake8==7.0.0 ; extra == "dev"
Requires-Dist: flit==3.9.0 ; extra == "dev"
Requires-Dist: mypy==1.9.0 ; extra == "dev"
Requires-Dist: sphinx==7.1.2 ; extra == "dev" and ( python_version < '3.9')
Requires-Dist: sphinx==7.3.7 ; extra == "dev" and ( python_version >= '3.9')
Requires-Dist: ufmt==2.5.1 ; extra == "dev"
Requires-Dist: usort==1.0.8.post1 ; extra == "dev"
Project-URL: Github, https://github.com/omnilib/sphinx-mdinclude
Provides-Extra: dev
